dynaroute/__init__.py
dynaroute/client.py
dynaroute/exceptions.py
dynaroute_client-1.0.2.dist-info/licenses/LICENSE
dynaroute_client-1.0.2.dist-info/METADATA
dynaroute_client-1.0.2.dist-info/WHEEL
dynaroute_client-1.0.2.dist-info/top_level.txt
dynaroute_client-1.0.2.dist-info/RECORD
