Metadata-Version: 2.4
Name: dynaroute-client
Version: 1.0.2
Summary: A client for interacting with the DynaRoute API.
Home-page: https://github.com/Vizuara-LLM/dynaroute-py
Author: Vizuara
Author-email: Vizuara <teamvizuara@gmail.com>
License: MIT
Project-URL: Homepage, https://github.com/Vizuara-LLM/dynaroute-py
Project-URL: Issues, https://github.com/Vizuara-LLM/dynaroute-py/issues
Classifier: Programming Language :: Python :: 3
Classifier: License :: OSI Approved :: MIT License
Classifier: Operating System :: OS Independent
Requires-Python: >=3.8
License-File: LICENSE
Requires-Dist: requests>=2.25.0
Dynamic: author
Dynamic: home-page
Dynamic: license-file
Dynamic: requires-python
